ytc/__init__.py
ytc-2025.8.5.dist-info/METADATA
ytc-2025.8.5.dist-info/WHEEL
ytc-2025.8.5.dist-info/top_level.txt
ytc-2025.8.5.dist-info/RECORD
