Metadata-Version: 2.4
Name: ytc
Version: 2025.8.5
Summary: fetch youtube cookies from remote api to use with yt_dlp .
Home-page: https://t.me/goldenxpris
Author: GoldenX
Author-email: 
Classifier: Programming Language :: Python :: 3
Classifier: License :: OSI Approved :: MIT License
Classifier: Operating System :: OS Independent
Requires-Python: >=3.8
Requires-Dist: requests
Requires-Dist: rich
Dynamic: author
Dynamic: classifier
Dynamic: description
Dynamic: description-content-type
Dynamic: home-page
Dynamic: requires-dist
Dynamic: requires-python
Dynamic: summary
